goat_plugins/dpsn/__init__.py
goat_plugins/dpsn/dpsn_client.py
goat_plugins/dpsn/parameters.py
goat_plugins/dpsn/service.py
goat_sdk_plugin_dpsn-0.1.0.dist-info/METADATA
goat_sdk_plugin_dpsn-0.1.0.dist-info/WHEEL
goat_sdk_plugin_dpsn-0.1.0.dist-info/RECORD
